mfdata/__init__.py
mfdata/api.py
mfdata/dates.py
mfdata/utils.py
mfdata-0.1.dev0.dist-info/METADATA
mfdata-0.1.dev0.dist-info/RECORD
mfdata-0.1.dev0.dist-info/WHEEL
mfdata-0.1.dev0.dist-info/top_level.txt
