Metadata-Version: 2.1
Name: mfdata
Version: 0.1.dev0
Summary: Database for macro-finance research.
Home-page: UNKNOWN
Author: Felix Han
Author-email: yh926@nyu.edu
License: MIT
Platform: UNKNOWN
Requires-Dist: numpy
Requires-Dist: pandas
Requires-Dist: matplotlib
Requires-Dist: seaborn
Requires-Dist: statsmodels
Requires-Dist: fredapi
Requires-Dist: wrds
